Workbook

Sheet Attendance
A1: ='Sales Report'!A1 -> NUAD THAI NEPAL Lazimpat
A3: ='Sales Report'!A4 -> Date : | B3: ='Sales Report'!B4 -> 46012
A4: ='Sales Report'!A5 -> Day: | B4: ='Sales Report'!B5 -> 46012
A6: Attendance Sheet
A7: SN | B7: Staff On Duty | C7: Signature | D7: Check In | E7: Check Out
A8: =IF(B8<>"", MAX(A$7:A7)+1, "")
A9: =IF(B9<>"", MAX(A$7:A8)+1, "")
A10: =IF(B10<>"", MAX(A$7:A9)+1, "")
A11: =IF(B11<>"", MAX(A$7:A10)+1, "")
A12: =IF(B12<>"", MAX(A$7:A11)+1, "")
A13: =IF(B13<>"", MAX(A$7:A12)+1, "")
A14: =IF(B14<>"", MAX(A$7:A13)+1, "")
A15: =IF(B15<>"", MAX(A$7:A14)+1, "")
A16: =IF(B16<>"", MAX(A$7:A15)+1, "")
A17: =IF(B17<>"", MAX(A$7:A16)+1, "")
A18: =IF(B18<>"", MAX(A$7:A17)+1, "")
A19: =IF(B19<>"", MAX(A$7:A18)+1, "")
... A28: =IF(B28<>"", MAX(A$7:A27)+1, "")
A38: SPA Signature Prepared By | F38: SPA Signature Verified By | L38: FO Signature
A39: Name: | F39: Name: | L39: Name:

Sheet Sales Report
A1: NUAD THAI NEPAL Lazimpat
J2: Actual Price | L2: 5800 | N2: Billing Price | O2: 1
A3: Report No: | B3: 21 | J3: Selling Price | L3: 5440 | N3: Price Here | O3: 1
A4: Date : | B4: 46012 | J4: Discount % | L4: =(L2-L3)/L2*100 -> 6.2068966 | N4: Qty | O4: =O2/O3 -> 1
A5: Day: | B5: =B4 -> 46012
A6: SN | B6: Guest Name | C6: Contact Number | D6: Room | E6: Time In | F6: Time Out | G6: Service | H6: Qty | I6: Rate | J6: Amount | K6: Dis % | L6: Dis Amount | M6: Final Amount | N6: Offers | O6: Payment | P6: Therapist Name | Q6: BOOKING | R6: Working Hrs | S6: Service Type | T6: Remarks | W6: Room | Y6: S.N | Z6: Service Name | AA6: Amount | AB6: Service Type | AC6: Working Hour | AE6: Discount | AG6: Staff List | AI6: Payment
A7: =IF(B7<>"", MAX(A$6:A6)+1, "") | I7: =IFERROR(VLOOKUP(G7,$Z$7:$AA$220,2,FALSE),0) -> 0 | J7: =H7*I7 -> 0 | L7: =J7*K7 -> 0 | M7: =if(or(O7="complementary",O7="Annual Pkg",O7="Deluxe Membership",O7="Premium Membership",O7="Hair Salon",O7="Customized Voucher",O7="Gift Voucher"),0,J7-L7) -> 0 | R7: =IFERROR(IF(VLOOKUP(G7, $Z$7:$AC$220, 4, FALSE) = 0, (F7 - E7) * 1440, VLOOKUP(G7, $Z$7:$AC$220, 4, FALSE)), (F7 - E7) * 1440) -> 0 | S7: =IFERROR(VLOOKUP(G7,$Z$7:$AC$220,3,FALSE),0) -> 0 | W7: LONDON | Y7: 1 | Z7: NUAD THAI TRADITIONAL HOT OIL MASSAGE-60 Min | AA7: 4200 | AB7: Spa | AC7: 60 | AE7: Manager | AG7: GANESH BISHUNKHE | AI7: Cash
A8: =IF(B8<>"", MAX(A$6:A7)+1, "") | I8: =IFERROR(VLOOKUP(G8,$Z$7:$AA$220,2,FALSE),0) -> 0 | J8: =H8*I8 -> 0 | L8: =J8*K8 -> 0 | M8: =if(or(O8="complementary",O8="Annual Pkg",O8="Deluxe Membership",O8="Premium Membership",O8="Hair Salon",O8="Customized Voucher",O8="Gift Voucher"),0,J8-L8) -> 0 | R8: =IFERROR(IF(VLOOKUP(G8, $Z$7:$AC$220, 4, FALSE) = 0, (F8 - E8) * 1440, VLOOKUP(G8, $Z$7:$AC$220, 4, FALSE)), (F8 - E8) * 1440) -> 0 | S8: =IFERROR(VLOOKUP(G8,$Z$7:$AC$220,3,FALSE),0) -> 0 | W8: OXFORD | Y8: 2 | Z8: NUAD THAI TRADITIONAL HOT OIL MASSAGE-90 Min | AA8: 5800 | AB8: Spa | AC8: 90 | AE8: DOSM | AG8: DEEPIKA TAMANG | AI8: Nabil Card
A9: =IF(B9<>"", MAX(A$6:A8)+1, "") | I9: =IFERROR(VLOOKUP(G9,$Z$7:$AA$220,2,FALSE),0) -> 0 | J9: =H9*I9 -> 0 | L9: =J9*K9 -> 0 | M9: =if(or(O9="complementary",O9="Annual Pkg",O9="Deluxe Membership",O9="Premium Membership",O9="Hair Salon",O9="Customized Voucher",O9="Gift Voucher"),0,J9-L9) -> 0 | R9: =IFERROR(IF(VLOOKUP(G9, $Z$7:$AC$220, 4, FALSE) = 0, (F9 - E9) * 1440, VLOOKUP(G9, $Z$7:$AC$220, 4, FALSE)), (F9 - E9) * 1440) -> 0 | S9: =IFERROR(VLOOKUP(G9,$Z$7:$AC$220,3,FALSE),0) -> 0 | W9: CHAINGMAI | Y9: 3 | Z9: NUAD THAI TRADITIONAL HOT OIL MASSAGE-120 Min | AA9: 7200 | AB9: Spa | AC9: 120 | AE9: Owner- Sujan Sir | AG9: ANJITA KARKI DARJI | AI9: Global IME Card
A10: =IF(B10<>"", MAX(A$6:A9)+1, "") | I10: =IFERROR(VLOOKUP(G10,$Z$7:$AA$220,2,FALSE),0) -> 0 | J10: =H10*I10 -> 0 | L10: =J10*K10 -> 0 | M10: =if(or(O10="complementary",O10="Annual Pkg",O10="Deluxe Membership",O10="Premium Membership",O10="Hair Salon",O10="Customized Voucher",O10="Gift Voucher"),0,J10-L10) -> 0 | R10: =IFERROR(IF(VLOOKUP(G10, $Z$7:$AC$220, 4, FALSE) = 0, (F10 - E10) * 1440, VLOOKUP(G10, $Z$7:$AC$220, 4, FALSE)), (F10 - E10) * 1440) -> 0 | S10: =IFERROR(VLOOKUP(G10,$Z$7:$AC$220,3,FALSE),0) -> 0 | V10: : | W10: PHUKET | Y10: 4 | Z10: NUAD THAI TRADITIONAL MASSAGE-60 Min | AA10: 4500 | AB10: Spa | AC10: 60 | AE10: Owner- Pratik Sir | AG10: JASMINE SHRESTHA | AI10: Nic Asia Card
A11: =IF(B11<>"", MAX(A$6:A10)+1, "") | I11: =IFERROR(VLOOKUP(G11,$Z$7:$AA$220,2,FALSE),0) -> 0 | J11: =H11*I11 -> 0 | L11: =J11*K11 -> 0 | M11: =if(or(O11="complementary",O11="Annual Pkg",O11="Deluxe Membership",O11="Premium Membership",O11="Hair Salon",O11="Customized Voucher",O11="Gift Voucher"),0,J11-L11) -> 0 | R11: =IFERROR(IF(VLOOKUP(G11, $Z$7:$AC$220, 4, FALSE) = 0, (F11 - E11) * 1440, VLOOKUP(G11, $Z$7:$AC$220, 4, FALSE)), (F11 - E11) * 1440) -> 0 | S11: =IFERROR(VLOOKUP(G11,$Z$7:$AC$220,3,FALSE),0) -> 0 | W11: BANGKOK | Y11: 5 | Z11: NUAD THAI TRADITIONAL MASSAGE-90 Min | AA11: 6100 | AB11: Spa | AC11: 90 | AE11: Therapist | AG11: NILA RAI | AI11: Fonepay
A12: =IF(B12<>"", MAX(A$6:A11)+1, "") | I12: =IFERROR(VLOOKUP(G12,$Z$7:$AA$220,2,FALSE),0) -> 0 | J12: =H12*I12 -> 0 | L12: =J12*K12 -> 0 | M12: =if(or(O12="complementary",O12="Annual Pkg",O12="Deluxe Membership",O12="Premium Membership",O12="Hair Salon",O12="Customized Voucher",O12="Gift Voucher"),0,J12-L12) -> 0 | R12: =IFERROR(IF(VLOOKUP(G12, $Z$7:$AC$220, 4, FALSE) = 0, (F12 - E12) * 1440, VLOOKUP(G12, $Z$7:$AC$220, 4, FALSE)), (F12 - E12) * 1440) -> 0 | S12: =IFERROR(VLOOKUP(G12,$Z$7:$AC$220,3,FALSE),0) -> 0 | W12: HUA HIN | Y12: 6 | Z12: NUAD THAI TRADITIONAL MASSAGE-120 Min | AA12: 7500 | AB12: Spa | AC12: 120 | AE12: GRO | AG12: PABITRA RAI | AI12: Credit
A13: =IF(B13<>"", MAX(A$6:A12)+1, "") | I13: =IFERROR(VLOOKUP(G13,$Z$7:$AA$220,2,FALSE),0) -> 0 | J13: =H13*I13 -> 0 | L13: =J13*K13 -> 0 | M13: =if(or(O13="complementary",O13="Annual Pkg",O13="Deluxe Membership",O13="Premium Membership",O13="Hair Salon",O13="Customized Voucher",O13="Gift Voucher"),0,J13-L13) -> 0 | R13: =IFERROR(IF(VLOOKUP(G13, $Z$7:$AC$220, 4, FALSE) = 0, (F13 - E13) * 1440, VLOOKUP(G13, $Z$7:$AC$220, 4, FALSE)), (F13 - E13) * 1440) -> 0 | S13: =IFERROR(VLOOKUP(G13,$Z$7:$AC$220,3,FALSE),0) -> 0 | W13: KATHMANDU | Y13: 7 | Z13: HEAD/BACK, NECK & SHOULDER-30 Min | AA13: 2500 | AB13: Spa | AC13: 30 | AE13: GRE | AG13: YAMSARA ALE MAGAR | AI13: Cheque
A14: =IF(B14<>"", MAX(A$6:A13)+1, "") | I14: =IFERROR(VLOOKUP(G14,$Z$7:$AA$220,2,FALSE),0) -> 0 | J14: =H14*I14 -> 0 | L14: =J14*K14 -> 0 | M14: =if(or(O14="complementary",O14="Annual Pkg",O14="Deluxe Membership",O14="Premium Membership",O14="Hair Salon",O14="Customized Voucher",O14="Gift Voucher"),0,J14-L14) -> 0 | R14: =IFERROR(IF(VLOOKUP(G14, $Z$7:$AC$220, 4, FALSE) = 0, (F14 - E14) * 1440, VLOOKUP(G14, $Z$7:$AC$220, 4, FALSE)), (F14 - E14) * 1440) -> 0 | S14: =IFERROR(VLOOKUP(G14,$Z$7:$AC$220,3,FALSE),0) -> 0 | W14: LUMBININ | Y14: 8 | Z14: HEAD/BACK, NECK & SHOULDER-45 Min | AA14: 3400 | AB14: Spa | AC14: 45 | AE14: Silver Membership | AG14: KAMALA TAMANG | AI14: Complementary
A15: =IF(B15<>"", MAX(A$6:A14)+1, "") | I15: =IFERROR(VLOOKUP(G15,$Z$7:$AA$220,2,FALSE),0) -> 0 | J15: =H15*I15 -> 0 | L15: =J15*K15 -> 0 | M15: =if(or(O15="complementary",O15="Annual Pkg",O15="Deluxe Membership",O15="Premium Membership",O15="Hair Salon",O15="Customized Voucher",O15="Gift Voucher"),0,J15-L15) -> 0 | R15: =IFERROR(IF(VLOOKUP(G15, $Z$7:$AC$220, 4, FALSE) = 0, (F15 - E15) * 1440, VLOOKUP(G15, $Z$7:$AC$220, 4, FALSE)), (F15 - E15) * 1440) -> 0 | S15: =IFERROR(VLOOKUP(G15,$Z$7:$AC$220,3,FALSE),0) -> 0 | W15: POKHARA | Y15: 9 | Z15: HEAD/BACK, NECK & SHOULDER-60 Min | AA15: 4200 | AB15: Spa | AC15: 60 | AE15: Hair Dresser | AG15: MANISHA TAMANG B | AI15: Annual Pkg
A16: =IF(B16<>"", MAX(A$6:A15)+1, "") | I16: =IFERROR(VLOOKUP(G16,$Z$7:$AA$220,2,FALSE),0) -> 0 | J16: =H16*I16 -> 0 | L16: =J16*K16 -> 0 | M16: =if(or(O16="complementary",O16="Annual Pkg",O16="Deluxe Membership",O16="Premium Membership",O16="Hair Salon",O16="Customized Voucher",O16="Gift Voucher"),0,J16-L16) -> 0 | R16: =IFERROR(IF(VLOOKUP(G16, $Z$7:$AC$220, 4, FALSE) = 0, (F16 - E16) * 1440, VLOOKUP(G16, $Z$7:$AC$220, 4, FALSE)), (F16 - E16) * 1440) -> 0 | S16: =IFERROR(VLOOKUP(G16,$Z$7:$AC$220,3,FALSE),0) -> 0 | W16: SALONS | Y16: 10 | Z16: FOOT REFLEXOLOGY-30 Min | AA16: 2400 | AB16: Spa | AC16: 30 | AE16: Current Offer | AG16: MANISHA TAMANG A | AI16: Deluxe Membership
A17: =IF(B17<>"", MAX(A$6:A16)+1, "") | I17: =IFERROR(VLOOKUP(G17,$Z$7:$AA$220,2,FALSE),0) -> 0 | J17: =H17*I17 -> 0 | L17: =J17*K17 -> 0 | M17: =if(or(O17="complementary",O17="Annual Pkg",O17="Deluxe Membership",O17="Premium Membership",O17="Hair Salon",O17="Customized Voucher",O17="Gift Voucher"),0,J17-L17) -> 0 | R17: =IFERROR(IF(VLOOKUP(G17, $Z$7:$AC$220, 4, FALSE) = 0, (F17 - E17) * 1440, VLOOKUP(G17, $Z$7:$AC$220, 4, FALSE)), (F17 - E17) * 1440) -> 0 | S17: =IFERROR(VLOOKUP(G17,$Z$7:$AC$220,3,FALSE),0) -> 0 | W17: PMM/FACIAL | Y17: 11 | Z17: FOOT REFLEXOLOGY-45 Min | AA17: 3300 | AB17: Spa | AC17: 45 | AG17: USHA TAMANG | AI17: Premium Membership
A18: =IF(B18<>"", MAX(A$6:A17)+1, "") | I18: =IFERROR(VLOOKUP(G18,$Z$7:$AA$220,2,FALSE),0) -> 0 | J18: =H18*I18 -> 0 | L18: =J18*K18 -> 0 | M18: =if(or(O18="complementary",O18="Annual Pkg",O18="Deluxe Membership",O18="Premium Membership",O18="Hair Salon",O18="Customized Voucher",O18="Gift Voucher"),0,J18-L18) -> 0 | R18: =IFERROR(IF(VLOOKUP(G18, $Z$7:$AC$220, 4, FALSE) = 0, (F18 - E18) * 1440, VLOOKUP(G18, $Z$7:$AC$220, 4, FALSE)), (F18 - E18) * 1440) -> 0 | S18: =IFERROR(VLOOKUP(G18,$Z$7:$AC$220,3,FALSE),0) -> 0 | W18: FOOT MASSAGE | Y18: 12 | Z18: FOOT REFLEXOLOGY-60 Min | AA18: 4100 | AB18: Spa | AC18: 60 | AG18: APSARA KHATRI | AI18: Hair Salon
A19: =IF(B19<>"", MAX(A$6:A18)+1, "") | I19: =IFERROR(VLOOKUP(G19,$Z$7:$AA$220,2,FALSE),0) -> 0 | J19: =H19*I19 -> 0 | L19: =J19*K19 -> 0 | M19: =if(or(O19="complementary",O19="Annual Pkg",O19="Deluxe Membership",O19="Premium Membership",O19="Hair Salon",O19="Customized Voucher",O19="Gift Voucher"),0,J19-L19) -> 0 | R19: =IFERROR(IF(VLOOKUP(G19, $Z$7:$AC$220, 4, FALSE) = 0, (F19 - E19) * 1440, VLOOKUP(G19, $Z$7:$AC$220, 4, FALSE)), (F19 - E19) * 1440) -> 0 | S19: =IFERROR(VLOOKUP(G19,$Z$7:$AC$220,3,FALSE),0) -> 0 | Y19: 13 | Z19: HAND REFLEXOLOGY-30 Min | AA19: 2500 | AB19: Spa | AC19: 30 | AG19: DEVINA KARKI | AI19: Customized Voucher
A20: =IF(B20<>"", MAX(A$6:A19)+1, "") | I20: =IFERROR(VLOOKUP(G20,$Z$7:$AA$220,2,FALSE),0) -> 0 | J20: =H20*I20 -> 0 | L20: =J20*K20 -> 0 | M20: =if(or(O20="complementary",O20="Annual Pkg",O20="Deluxe Membership",O20="Premium Membership",O20="Hair Salon",O20="Customized Voucher",O20="Gift Voucher"),0,J20-L20) -> 0 | R20: =IFERROR(IF(VLOOKUP(G20, $Z$7:$AC$220, 4, FALSE) = 0, (F20 - E20) * 1440, VLOOKUP(G20, $Z$7:$AC$220, 4, FALSE)), (F20 - E20) * 1440) -> 0 | S20: =IFERROR(VLOOKUP(G20,$Z$7:$AC$220,3,FALSE),0) -> 0 | Y20: 14 | Z20: HEAD MASSAGE-30 Min | AA20: 2500 | AB20: Spa | AC20: 30 | AG20: MANJU POUDEL | AI20: Gift Voucher
A21: =IF(B21<>"", MAX(A$6:A20)+1, "") | I21: =IFERROR(VLOOKUP(G21,$Z$7:$AA$220,2,FALSE),0) -> 0 | J21: =H21*I21 -> 0 | L21: =J21*K21 -> 0 | M21: =if(or(O21="complementary",O21="Annual Pkg",O21="Deluxe Membership",O21="Premium Membership",O21="Hair Salon",O21="Customized Voucher",O21="Gift Voucher"),0,J21-L21) -> 0 | R21: =IFERROR(IF(VLOOKUP(G21, $Z$7:$AC$220, 4, FALSE) = 0, (F21 - E21) * 1440, VLOOKUP(G21, $Z$7:$AC$220, 4, FALSE)), (F21 - E21) * 1440) -> 0 | S21: =IFERROR(VLOOKUP(G21,$Z$7:$AC$220,3,FALSE),0) -> 0 | Y21: 15 | Z21: ENERGISE BODY-90 Min | AA21: 7000 | AB21: Spa | AC21: 90 | AG21: SIRMAYA GURUNG
A22: =IF(B22<>"", MAX(A$6:A21)+1, "") | I22: =IFERROR(VLOOKUP(G22,$Z$7:$AA$220,2,FALSE),0) -> 0 | J22: =H22*I22 -> 0 | L22: =J22*K22 -> 0 | M22: =if(or(O22="complementary",O22="Annual Pkg",O22="Deluxe Membership",O22="Premium Membership",O22="Hair Salon",O22="Customized Voucher",O22="Gift Voucher"),0,J22-L22) -> 0 | R22: =IFERROR(IF(VLOOKUP(G22, $Z$7:$AC$220, 4, FALSE) = 0, (F22 - E22) * 1440, VLOOKUP(G22, $Z$7:$AC$220, 4, FALSE)), (F22 - E22) * 1440) -> 0 | S22: =IFERROR(VLOOKUP(G22,$Z$7:$AC$220,3,FALSE),0) -> 0 | Y22: 16 | Z22: ENERGISE BODY-120 Min | AA22: 8400 | AB22: Spa | AC22: 120 | AG22: NISSA KUMARI MAGAR
A23: =IF(B23<>"", MAX(A$6:A22)+1, "") | I23: =IFERROR(VLOOKUP(G23,$Z$7:$AA$220,2,FALSE),0) -> 0 | J23: =H23*I23 -> 0 | L23: =J23*K23 -> 0 | M23: =if(or(O23="complementary",O23="Annual Pkg",O23="Deluxe Membership",O23="Premium Membership",O23="Hair Salon",O23="Customized Voucher",O23="Gift Voucher"),0,J23-L23) -> 0 | R23: =IFERROR(IF(VLOOKUP(G23, $Z$7:$AC$220, 4, FALSE) = 0, (F23 - E23) * 1440, VLOOKUP(G23, $Z$7:$AC$220, 4, FALSE)), (F23 - E23) * 1440) -> 0 | S23: =IFERROR(VLOOKUP(G23,$Z$7:$AC$220,3,FALSE),0) -> 0 | Y23: 17 | Z23: RELAX BODY-90 Min | AA23: 6700 | AB23: Spa | AC23: 90 | AG23: SANTOSH KHADKA
A24: =IF(B24<>"", MAX(A$6:A23)+1, "") | I24: =IFERROR(VLOOKUP(G24,$Z$7:$AA$220,2,FALSE),0) -> 0 | J24: =H24*I24 -> 0 | L24: =J24*K24 -> 0 | M24: =if(or(O24="complementary",O24="Annual Pkg",O24="Deluxe Membership",O24="Premium Membership",O24="Hair Salon",O24="Customized Voucher",O24="Gift Voucher"),0,J24-L24) -> 0 | R24: =IFERROR(IF(VLOOKUP(G24, $Z$7:$AC$220, 4, FALSE) = 0, (F24 - E24) * 1440, VLOOKUP(G24, $Z$7:$AC$220, 4, FALSE)), (F24 - E24) * 1440) -> 0 | S24: =IFERROR(VLOOKUP(G24,$Z$7:$AC$220,3,FALSE),0) -> 0 | Y24: 18 | Z24: RELAX BODY-120 Min | AA24: 8100 | AB24: Spa | AC24: 120 | AG24: SUSHILA RAI
A25: =IF(B25<>"", MAX(A$6:A24)+1, "") | I25: =IFERROR(VLOOKUP(G25,$Z$7:$AA$220,2,FALSE),0) -> 0 | J25: =H25*I25 -> 0 | L25: =J25*K25 -> 0 | M25: =if(or(O25="complementary",O25="Annual Pkg",O25="Deluxe Membership",O25="Premium Membership",O25="Hair Salon",O25="Customized Voucher",O25="Gift Voucher"),0,J25-L25) -> 0 | R25: =IFERROR(IF(VLOOKUP(G25, $Z$7:$AC$220, 4, FALSE) = 0, (F25 - E25) * 1440, VLOOKUP(G25, $Z$7:$AC$220, 4, FALSE)), (F25 - E25) * 1440) -> 0 | S25: =IFERROR(VLOOKUP(G25,$Z$7:$AC$220,3,FALSE),0) -> 0 | Y25: 19 | Z25: PAIN RELEASE-60 Min | AA25: 4500 | AB25: Spa | AC25: 60 | AG25: ADITYA JUNG RANA
A26: =IF(B26<>"", MAX(A$6:A25)+1, "") | I26: =IFERROR(VLOOKUP(G26,$Z$7:$AA$220,2,FALSE),0) -> 0 | J26: =H26*I26 -> 0 | L26: =J26*K26 -> 0 | M26: =if(or(O26="complementary",O26="Annual Pkg",O26="Deluxe Membership",O26="Premium Membership",O26="Hair Salon",O26="Customized Voucher",O26="Gift Voucher"),0,J26-L26) -> 0 | R26: =IFERROR(IF(VLOOKUP(G26, $Z$7:$AC$220, 4, FALSE) = 0, (F26 - E26) * 1440, VLOOKUP(G26, $Z$7:$AC$220, 4, FALSE)), (F26 - E26) * 1440) -> 0 | S26: =IFERROR(VLOOKUP(G26,$Z$7:$AC$220,3,FALSE),0) -> 0 | Y26: 20 | Z26: PAIN RELEASE-90 Min | AA26: 6000 | AB26: Spa | AC26: 90 | AG26: TRISHA ACHARYA
A27: =IF(B27<>"", MAX(A$6:A26)+1, "") | I27: =IFERROR(VLOOKUP(G27,$Z$7:$AA$220,2,FALSE),0) -> 0 | J27: =H27*I27 -> 0 | L27: =J27*K27 -> 0 | M27: =if(or(O27="complementary",O27="Annual Pkg",O27="Deluxe Membership",O27="Premium Membership",O27="Hair Salon",O27="Customized Voucher",O27="Gift Voucher"),0,J27-L27) -> 0 | R27: =IFERROR(IF(VLOOKUP(G27, $Z$7:$AC$220, 4, FALSE) = 0, (F27 - E27) * 1440, VLOOKUP(G27, $Z$7:$AC$220, 4, FALSE)), (F27 - E27) * 1440) -> 0 | S27: =IFERROR(VLOOKUP(G27,$Z$7:$AC$220,3,FALSE),0) -> 0 | Y27: 21 | Z27: PAIN RELEASE-120 Min | AA27: 7400 | AB27: Spa | AC27: 120 | AG27: NIRAJ BOGATI
A28: =IF(B28<>"", MAX(A$6:A27)+1, "") | I28: =IFERROR(VLOOKUP(G28,$Z$7:$AA$220,2,FALSE),0) -> 0 | J28: =H28*I28 -> 0 | L28: =J28*K28 -> 0 | M28: =if(or(O28="complementary",O28="Annual Pkg",O28="Deluxe Membership",O28="Premium Membership",O28="Hair Salon",O28="Customized Voucher",O28="Gift Voucher"),0,J28-L28) -> 0 | R28: =IFERROR(IF(VLOOKUP(G28, $Z$7:$AC$220, 4, FALSE) = 0, (F28 - E28) * 1440, VLOOKUP(G28, $Z$7:$AC$220, 4, FALSE)), (F28 - E28) * 1440) -> 0 | S28: =IFERROR(VLOOKUP(G28,$Z$7:$AC$220,3,FALSE),0) -> 0 | Y28: 22 | Z28: BANGKOK-90 Min | AA28: 6600 | AB28: Spa | AC28: 90 | AG28: PUSHPA BARAM
A29: =IF(B29<>"", MAX(A$6:A28)+1, "") | I29: =IFERROR(VLOOKUP(G29,$Z$7:$AA$220,2,FALSE),0) -> 0 | J29: =H29*I29 -> 0 | L29: =J29*K29 -> 0 | M29: =if(or(O29="complementary",O29="Annual Pkg",O29="Deluxe Membership",O29="Premium Membership",O29="Hair Salon",O29="Customized Voucher",O29="Gift Voucher"),0,J29-L29) -> 0 | R29: =IFERROR(IF(VLOOKUP(G29, $Z$7:$AC$220, 4, FALSE) = 0, (F29 - E29) * 1440, VLOOKUP(G29, $Z$7:$AC$220, 4, FALSE)), (F29 - E29) * 1440) -> 0 | S29: =IFERROR(VLOOKUP(G29,$Z$7:$AC$220,3,FALSE),0) -> 0 | Y29: 23 | Z29: BANGKOK-120 Min | AA29: 8200 | AB29: Spa | AC29: 120 | AG29: KALA BARAM
A30: =IF(B30<>"", MAX(A$6:A29)+1, "") | I30: =IFERROR(VLOOKUP(G30,$Z$7:$AA$220,2,FALSE),0) -> 0 | J30: =H30*I30 -> 0 | L30: =J30*K30 -> 0 | M30: =if(or(O30="complementary",O30="Annual Pkg",O30="Deluxe Membership",O30="Premium Membership",O30="Hair Salon",O30="Customized Voucher",O30="Gift Voucher"),0,J30-L30) -> 0 | R30: =IFERROR(IF(VLOOKUP(G30, $Z$7:$AC$220, 4, FALSE) = 0, (F30 - E30) * 1440, VLOOKUP(G30, $Z$7:$AC$220, 4, FALSE)), (F30 - E30) * 1440) -> 0 | S30: =IFERROR(VLOOKUP(G30,$Z$7:$AC$220,3,FALSE),0) -> 0 | Y30: 24 | Z30: OXFORD-120 Min | AA30: 8400 | AB30: Spa & Beauty Salon Combo | AC30: 120 | AG30: ASHMI THING TAMANG
A31: =IF(B31<>"", MAX(A$6:A30)+1, "") | I31: =IFERROR(VLOOKUP(G31,$Z$7:$AA$220,2,FALSE),0) -> 0 | J31: =H31*I31 -> 0 | L31: =J31*K31 -> 0 | M31: =if(or(O31="complementary",O31="Annual Pkg",O31="Deluxe Membership",O31="Premium Membership",O31="Hair Salon",O31="Customized Voucher",O31="Gift Voucher"),0,J31-L31) -> 0 | R31: =IFERROR(IF(VLOOKUP(G31, $Z$7:$AC$220, 4, FALSE) = 0, (F31 - E31) * 1440, VLOOKUP(G31, $Z$7:$AC$220, 4, FALSE)), (F31 - E31) * 1440) -> 0 | S31: =IFERROR(VLOOKUP(G31,$Z$7:$AC$220,3,FALSE),0) -> 0 | Y31: 25 | Z31: OXFORD-150 Min | AA31: 10700 | AB31: Spa & Beauty Salon Combo | AC31: 150 | AG31: ANISHA THAKURI
A32: =IF(B32<>"", MAX(A$6:A31)+1, "") | I32: =IFERROR(VLOOKUP(G32,$Z$7:$AA$220,2,FALSE),0) -> 0 | J32: =H32*I32 -> 0 | L32: =J32*K32 -> 0 | M32: =if(or(O32="complementary",O32="Annual Pkg",O32="Deluxe Membership",O32="Premium Membership",O32="Hair Salon",O32="Customized Voucher",O32="Gift Voucher"),0,J32-L32) -> 0 | R32: =IFERROR(IF(VLOOKUP(G32, $Z$7:$AC$220, 4, FALSE) = 0, (F32 - E32) * 1440, VLOOKUP(G32, $Z$7:$AC$220, 4, FALSE)), (F32 - E32) * 1440) -> 0 | S32: =IFERROR(VLOOKUP(G32,$Z$7:$AC$220,3,FALSE),0) -> 0 | Y32: 26 | Z32: LONDON-180 Min | AA32: 9900 | AB32: Spa & Beauty Salon Combo | AC32: 150 | AG32: RABIN MAJHI
... A40: =IF(B40<>"", MAX(A$6:A39)+1, "") | I40: =IFERROR(VLOOKUP(G40,$Z$7:$AA$220,2,FALSE),0) -> 0 | J40: =H40*I40 -> 0 | L40: =J40*K40 -> 0 | M40: =if(or(O40="complementary",O40="Annual Pkg",O40="Deluxe Membership",O40="Premium Membership",O40="Hair Salon",O40="Customized Voucher",O40="Gift Voucher"),0,J40-L40) -> 0 | R40: =IFERROR(IF(VLOOKUP(G40, $Z$7:$AC$220, 4, FALSE) = 0, (F40 - E40) * 1440, VLOOKUP(G40, $Z$7:$AC$220, 4, FALSE)), (F40 - E40) * 1440) -> 0 | S40: =IFERROR(VLOOKUP(G40,$Z$7:$AC$220,3,FALSE),0) -> 0 | Y40: 34 | Z40: Facial-Shine Stop Treatment(Oily, Acnes, Open pores skin) | AA40: 6500 | AB40: Beauty Salon | AC40: 90 | AG40: DOLMA LOPCHAN
A41: =IF(B41<>"", MAX(A$6:A40)+1, "") | I41: =IFERROR(VLOOKUP(G41,$Z$7:$AA$220,2,FALSE),0) -> 0 | J41: =H41*I41 -> 0 | L41: =J41*K41 -> 0 | M41: =if(or(O41="complementary",O41="Annual Pkg",O41="Deluxe Membership",O41="Premium Membership",O41="Hair Salon",O41="Customized Voucher",O41="Gift Voucher"),0,J41-L41) -> 0 | R41: =IFERROR(IF(VLOOKUP(G41, $Z$7:$AC$220, 4, FALSE) = 0, (F41 - E41) * 1440, VLOOKUP(G41, $Z$7:$AC$220, 4, FALSE)), (F41 - E41) * 1440) -> 0 | S41: =IFERROR(VLOOKUP(G41,$Z$7:$AC$220,3,FALSE),0) -> 0 | Y41: 35 | Z41: Facial-Nacar Treatment(Lightening, Brightening, Pigmentation) | AA41: 8000 | AB41: Beauty Salon | AC41: 90
A42: =IF(B42<>"", MAX(A$6:A41)+1, "") | I42: =IFERROR(VLOOKUP(G42,$Z$7:$AA$220,2,FALSE),0) -> 0 | J42: =H42*I42 -> 0 | L42: =J42*K42 -> 0 | M42: =if(or(O42="complementary",O42="Annual Pkg",O42="Deluxe Membership",O42="Premium Membership",O42="Hair Salon",O42="Customized Voucher",O42="Gift Voucher"),0,J42-L42) -> 0 | R42: =IFERROR(IF(VLOOKUP(G42, $Z$7:$AC$220, 4, FALSE) = 0, (F42 - E42) * 1440, VLOOKUP(G42, $Z$7:$AC$220, 4, FALSE)), (F42 - E42) * 1440) -> 0 | S42: =IFERROR(VLOOKUP(G42,$Z$7:$AC$220,3,FALSE),0) -> 0 | Y42: 36 | Z42: Facial-Ocean Miracle Treatment(Anti-Ageing & Firming) | AA42: 7000 | AB42: Beauty Salon | AC42: 90
A43: =IF(B43<>"", MAX(A$6:A42)+1, "") | I43: =IFERROR(VLOOKUP(G43,$Z$7:$AA$220,2,FALSE),0) -> 0 | J43: =H43*I43 -> 0 | L43: =J43*K43 -> 0 | M43: =if(or(O43="complementary",O43="Annual Pkg",O43="Deluxe Membership",O43="Premium Membership",O43="Hair Salon",O43="Customized Voucher",O43="Gift Voucher"),0,J43-L43) -> 0 | R43: =IFERROR(IF(VLOOKUP(G43, $Z$7:$AC$220, 4, FALSE) = 0, (F43 - E43) * 1440, VLOOKUP(G43, $Z$7:$AC$220, 4, FALSE)), (F43 - E43) * 1440) -> 0 | S43: =IFERROR(VLOOKUP(G43,$Z$7:$AC$220,3,FALSE),0) -> 0 | Y43: 37 | Z43: Facial-Goji Treatment(For dry skin – Antioxidant /Antioxidante) | AA43: 6500 | AB43: Beauty Salon | AC43: 90
A44: =IF(B44<>"", MAX(A$6:A43)+1, "") | I44: =IFERROR(VLOOKUP(G44,$Z$7:$AA$220,2,FALSE),0) -> 0 | J44: =H44*I44 -> 0 | L44: =J44*K44 -> 0 | M44: =if(or(O44="complementary",O44="Annual Pkg",O44="Deluxe Membership",O44="Premium Membership",O44="Hair Salon",O44="Customized Voucher",O44="Gift Voucher"),0,J44-L44) -> 0 | R44: =IFERROR(IF(VLOOKUP(G44, $Z$7:$AC$220, 4, FALSE) = 0, (F44 - E44) * 1440, VLOOKUP(G44, $Z$7:$AC$220, 4, FALSE)), (F44 - E44) * 1440) -> 0 | S44: =IFERROR(VLOOKUP(G44,$Z$7:$AC$220,3,FALSE),0) -> 0 | Y44: 38 | Z44: Facial-Purifying Treatment(For dull and dehydrated skin) | AA44: 6500 | AB44: Beauty Salon | AC44: 90
A45: =IF(B45<>"", MAX(A$6:A44)+1, "") | I45: =IFERROR(VLOOKUP(G45,$Z$7:$AA$220,2,FALSE),0) -> 0 | J45: =H45*I45 -> 0 | L45: =J45*K45 -> 0 | M45: =if(or(O45="complementary",O45="Annual Pkg",O45="Deluxe Membership",O45="Premium Membership",O45="Hair Salon",O45="Customized Voucher",O45="Gift Voucher"),0,J45-L45) -> 0 | R45: =IFERROR(IF(VLOOKUP(G45, $Z$7:$AC$220, 4, FALSE) = 0, (F45 - E45) * 1440, VLOOKUP(G45, $Z$7:$AC$220, 4, FALSE)), (F45 - E45) * 1440) -> 0 | S45: =IFERROR(VLOOKUP(G45,$Z$7:$AC$220,3,FALSE),0) -> 0 | Y45: 39 | Z45: Facial-Mini Facial(Casmara) | AA45: 3500 | AB45: Beauty Salon | AC45: 60
A46: =IF(B46<>"", MAX(A$6:A45)+1, "") | I46: =IFERROR(VLOOKUP(G46,$Z$7:$AA$220,2,FALSE),0) -> 0 | J46: =H46*I46 -> 0 | L46: =J46*K46 -> 0 | M46: =if(or(O46="complementary",O46="Annual Pkg",O46="Deluxe Membership",O46="Premium Membership",O46="Hair Salon",O46="Customized Voucher",O46="Gift Voucher"),0,J46-L46) -> 0 | R46: =IFERROR(IF(VLOOKUP(G46, $Z$7:$AC$220, 4, FALSE) = 0, (F46 - E46) * 1440, VLOOKUP(G46, $Z$7:$AC$220, 4, FALSE)), (F46 - E46) * 1440) -> 0 | S46: =IFERROR(VLOOKUP(G46,$Z$7:$AC$220,3,FALSE),0) -> 0 | Y46: 40 | Z46: Facial-Mini Facial(Lotus) | AA46: 1500 | AB46: Beauty Salon | AC46: 30
A47: =IF(B47<>"", MAX(A$6:A46)+1, "") | I47: =IFERROR(VLOOKUP(G47,$Z$7:$AA$220,2,FALSE),0) -> 0 | J47: =H47*I47 -> 0 | L47: =J47*K47 -> 0 | M47: =if(or(O47="complementary",O47="Annual Pkg",O47="Deluxe Membership",O47="Premium Membership",O47="Hair Salon",O47="Customized Voucher",O47="Gift Voucher"),0,J47-L47) -> 0 | R47: =IFERROR(IF(VLOOKUP(G47, $Z$7:$AC$220, 4, FALSE) = 0, (F47 - E47) * 1440, VLOOKUP(G47, $Z$7:$AC$220, 4, FALSE)), (F47 - E47) * 1440) -> 0 | S47: =IFERROR(VLOOKUP(G47,$Z$7:$AC$220,3,FALSE),0) -> 0 | Y47: 41 | Z47: Facial-Glowdermie Facial(Ionising facial for enhanced skin glow) | AA47: 2500 | AB47: Beauty Salon | AC47: 60
A48: =IF(B48<>"", MAX(A$6:A47)+1, "") | I48: =IFERROR(VLOOKUP(G48,$Z$7:$AA$220,2,FALSE),0) -> 0 | J48: =H48*I48 -> 0 | L48: =J48*K48 -> 0 | M48: =if(or(O48="complementary",O48="Annual Pkg",O48="Deluxe Membership",O48="Premium Membership",O48="Hair Salon",O48="Customized Voucher",O48="Gift Voucher"),0,J48-L48) -> 0 | R48: =IFERROR(IF(VLOOKUP(G48, $Z$7:$AC$220, 4, FALSE) = 0, (F48 - E48) * 1440, VLOOKUP(G48, $Z$7:$AC$220, 4, FALSE)), (F48 - E48) * 1440) -> 0 | S48: =IFERROR(VLOOKUP(G48,$Z$7:$AC$220,3,FALSE),0) -> 0 | Y48: 42 | Z48: Facial-Goldsheen(Facial incorporating actives for instant gold-like lustre) | AA48: 3500 | AB48: Beauty Salon | AC48: 60
A49: =IF(B49<>"", MAX(A$6:A48)+1, "") | I49: =IFERROR(VLOOKUP(G49,$Z$7:$AA$220,2,FALSE),0) -> 0 | J49: =H49*I49 -> 0 | L49: =J49*K49 -> 0 | M49: =if(or(O49="complementary",O49="Annual Pkg",O49="Deluxe Membership",O49="Premium Membership",O49="Hair Salon",O49="Customized Voucher",O49="Gift Voucher"),0,J49-L49) -> 0 | R49: =IFERROR(IF(VLOOKUP(G49, $Z$7:$AC$220, 4, FALSE) = 0, (F49 - E49) * 1440, VLOOKUP(G49, $Z$7:$AC$220, 4, FALSE)), (F49 - E49) * 1440) -> 0 | S49: =IFERROR(VLOOKUP(G49,$Z$7:$AC$220,3,FALSE),0) -> 0 | Y49: 43 | Z49: Facial-Dipigmentone(Exclusive treatment for removing pigmentation and other spots using advanced activities) | AA49: 2500 | AB49: Beauty Salon | AC49: 60
A50: =IF(B50<>"", MAX(A$6:A49)+1, "") | I50: =IFERROR(VLOOKUP(G50,$Z$7:$AA$220,2,FALSE),0) -> 0 | J50: =H50*I50 -> 0 | L50: =J50*K50 -> 0 | M50: =if(or(O50="complementary",O50="Annual Pkg",O50="Deluxe Membership",O50="Premium Membership",O50="Hair Salon",O50="Customized Voucher",O50="Gift Voucher"),0,J50-L50) -> 0 | R50: =IFERROR(IF(VLOOKUP(G50, $Z$7:$AC$220, 4, FALSE) = 0, (F50 - E50) * 1440, VLOOKUP(G50, $Z$7:$AC$220, 4, FALSE)), (F50 - E50) * 1440) -> 0 | S50: =IFERROR(VLOOKUP(G50,$Z$7:$AC$220,3,FALSE),0) -> 0 | Y50: 44 | Z50: Facial-Acnex(Advanced pimple & acne treatment) | AA50: 2500 | AB50: Beauty Salon | AC50: 60
A51: =IF(B51<>"", MAX(A$6:A50)+1, "") | I51: =IFERROR(VLOOKUP(G51,$Z$7:$AA$220,2,FALSE),0) -> 0 | J51: =H51*I51 -> 0 | L51: =J51*K51 -> 0 | M51: =if(or(O51="complementary",O51="Annual Pkg",O51="Deluxe Membership",O51="Premium Membership",O51="Hair Salon",O51="Customized Voucher",O51="Gift Voucher"),0,J51-L51) -> 0 | R51: =IFERROR(IF(VLOOKUP(G51, $Z$7:$AC$220, 4, FALSE) = 0, (F51 - E51) * 1440, VLOOKUP(G51, $Z$7:$AC$220, 4, FALSE)), (F51 - E51) * 1440) -> 0 | S51: =IFERROR(VLOOKUP(G51,$Z$7:$AC$220,3,FALSE),0) -> 0 | Y51: 45 | Z51: Standard Hair Waxing- Full Arms | AA51: 1200 | AB51: Beauty Salon
A52: =IF(B52<>"", MAX(A$6:A51)+1, "") | I52: =IFERROR(VLOOKUP(G52,$Z$7:$AA$220,2,FALSE),0) -> 0 | J52: =H52*I52 -> 0 | L52: =J52*K52 -> 0 | M52: =if(or(O52="complementary",O52="Annual Pkg",O52="Deluxe Membership",O52="Premium Membership",O52="Hair Salon",O52="Customized Voucher",O52="Gift Voucher"),0,J52-L52) -> 0 | R52: =IFERROR(IF(VLOOKUP(G52, $Z$7:$AC$220, 4, FALSE) = 0, (F52 - E52) * 1440, VLOOKUP(G52, $Z$7:$AC$220, 4, FALSE)), (F52 - E52) * 1440) -> 0 | S52: =IFERROR(VLOOKUP(G52,$Z$7:$AC$220,3,FALSE),0) -> 0 | Y52: 46 | Z52: Standard Hair Waxing- Half Arms | AA52: 800 | AB52: Beauty Salon
A53: =IF(B53<>"", MAX(A$6:A52)+1, "") | I53: =IFERROR(VLOOKUP(G53,$Z$7:$AA$220,2,FALSE),0) -> 0 | J53: =H53*I53 -> 0 | L53: =J53*K53 -> 0 | M53: =if(or(O53="complementary",O53="Annual Pkg",O53="Deluxe Membership",O53="Premium Membership",O53="Hair Salon",O53="Customized Voucher",O53="Gift Voucher"),0,J53-L53) -> 0 | R53: =IFERROR(IF(VLOOKUP(G53, $Z$7:$AC$220, 4, FALSE) = 0, (F53 - E53) * 1440, VLOOKUP(G53, $Z$7:$AC$220, 4, FALSE)), (F53 - E53) * 1440) -> 0 | S53: =IFERROR(VLOOKUP(G53,$Z$7:$AC$220,3,FALSE),0) -> 0 | Y53: 47 | Z53: Standard Hair Waxing- Under Arms | AA53: 600 | AB53: Beauty Salon
A54: =IF(B54<>"", MAX(A$6:A53)+1, "") | I54: =IFERROR(VLOOKUP(G54,$Z$7:$AA$220,2,FALSE),0) -> 0 | J54: =H54*I54 -> 0 | L54: =J54*K54 -> 0 | M54: =if(or(O54="complementary",O54="Annual Pkg",O54="Deluxe Membership",O54="Premium Membership",O54="Hair Salon",O54="Customized Voucher",O54="Gift Voucher"),0,J54-L54) -> 0 | R54: =IFERROR(IF(VLOOKUP(G54, $Z$7:$AC$220, 4, FALSE) = 0, (F54 - E54) * 1440, VLOOKUP(G54, $Z$7:$AC$220, 4, FALSE)), (F54 - E54) * 1440) -> 0 | S54: =IFERROR(VLOOKUP(G54,$Z$7:$AC$220,3,FALSE),0) -> 0 | Y54: 48 | Z54: Standard Hair Waxing- Chest | AA54: 1200 | AB54: Beauty Salon
A55: =IF(B55<>"", MAX(A$6:A54)+1, "") | I55: =IFERROR(VLOOKUP(G55,$Z$7:$AA$220,2,FALSE),0) -> 0 | J55: =H55*I55 -> 0 | L55: =J55*K55 -> 0 | M55: =if(or(O55="complementary",O55="Annual Pkg",O55="Deluxe Membership",O55="Premium Membership",O55="Hair Salon",O55="Customized Voucher",O55="Gift Voucher"),0,J55-L55) -> 0 | R55: =IFERROR(IF(VLOOKUP(G55, $Z$7:$AC$220, 4, FALSE) = 0, (F55 - E55) * 1440, VLOOKUP(G55, $Z$7:$AC$220, 4, FALSE)), (F55 - E55) * 1440) -> 0 | S55: =IFERROR(VLOOKUP(G55,$Z$7:$AC$220,3,FALSE),0) -> 0 | Y55: 49 | Z55: Standard Hair Waxing- Half Leg | AA55: 1200 | AB55: Beauty Salon
A56: =IF(B56<>"", MAX(A$6:A55)+1, "") | I56: =IFERROR(VLOOKUP(G56,$Z$7:$AA$220,2,FALSE),0) -> 0 | J56: =H56*I56 -> 0 | L56: =J56*K56 -> 0 | M56: =if(or(O56="complementary",O56="Annual Pkg",O56="Deluxe Membership",O56="Premium Membership",O56="Hair Salon",O56="Customized Voucher",O56="Gift Voucher"),0,J56-L56) -> 0 | R56: =IFERROR(IF(VLOOKUP(G56, $Z$7:$AC$220, 4, FALSE) = 0, (F56 - E56) * 1440, VLOOKUP(G56, $Z$7:$AC$220, 4, FALSE)), (F56 - E56) * 1440) -> 0 | S56: =IFERROR(VLOOKUP(G56,$Z$7:$AC$220,3,FALSE),0) -> 0 | Y56: 50 | Z56: Standard Hair Waxing- Full Legs | AA56: 1800 | AB56: Beauty Salon
A57: =IF(B57<>"", MAX(A$6:A56)+1, "") | I57: =IFERROR(VLOOKUP(G57,$Z$7:$AA$220,2,FALSE),0) -> 0 | J57: =H57*I57 -> 0 | L57: =J57*K57 -> 0 | M57: =if(or(O57="complementary",O57="Annual Pkg",O57="Deluxe Membership",O57="Premium Membership",O57="Hair Salon",O57="Customized Voucher",O57="Gift Voucher"),0,J57-L57) -> 0 | R57: =IFERROR(IF(VLOOKUP(G57, $Z$7:$AC$220, 4, FALSE) = 0, (F57 - E57) * 1440, VLOOKUP(G57, $Z$7:$AC$220, 4, FALSE)), (F57 - E57) * 1440) -> 0 | S57: =IFERROR(VLOOKUP(G57,$Z$7:$AC$220,3,FALSE),0) -> 0 | Y57: 51 | Z57: Standard Hair Waxing- Stomach | AA57: 1000 | AB57: Beauty Salon
A58: =IF(B58<>"", MAX(A$6:A57)+1, "") | I58: =IFERROR(VLOOKUP(G58,$Z$7:$AA$220,2,FALSE),0) -> 0 | J58: =H58*I58 -> 0 | L58: =J58*K58 -> 0 | M58: =if(or(O58="complementary",O58="Annual Pkg",O58="Deluxe Membership",O58="Premium Membership",O58="Hair Salon",O58="Customized Voucher",O58="Gift Voucher"),0,J58-L58) -> 0 | R58: =IFERROR(IF(VLOOKUP(G58, $Z$7:$AC$220, 4, FALSE) = 0, (F58 - E58) * 1440, VLOOKUP(G58, $Z$7:$AC$220, 4, FALSE)), (F58 - E58) * 1440) -> 0 | S58: =IFERROR(VLOOKUP(G58,$Z$7:$AC$220,3,FALSE),0) -> 0 | Y58: 52 | Z58: Standard Hair Waxing- Full Back | AA58: 1200 | AB58: Beauty Salon
A59: =IF(B59<>"", MAX(A$6:A58)+1, "") | I59: =IFERROR(VLOOKUP(G59,$Z$7:$AA$220,2,FALSE),0) -> 0 | J59: =H59*I59 -> 0 | L59: =J59*K59 -> 0 | M59: =if(or(O59="complementary",O59="Annual Pkg",O59="Deluxe Membership",O59="Premium Membership",O59="Hair Salon",O59="Customized Voucher",O59="Gift Voucher"),0,J59-L59) -> 0 | R59: =IFERROR(IF(VLOOKUP(G59, $Z$7:$AC$220, 4, FALSE) = 0, (F59 - E59) * 1440, VLOOKUP(G59, $Z$7:$AC$220, 4, FALSE)), (F59 - E59) * 1440) -> 0 | S59: =IFERROR(VLOOKUP(G59,$Z$7:$AC$220,3,FALSE),0) -> 0 | Y59: 53 | Z59: Standard Hair Waxing- Bikini Line | AA59: 1000 | AB59: Beauty Salon
A60: =IF(B60<>"", MAX(A$6:A59)+1, "") | I60: =IFERROR(VLOOKUP(G60,$Z$7:$AA$220,2,FALSE),0) -> 0 | J60: =H60*I60 -> 0 | L60: =J60*K60 -> 0 | M60: =if(or(O60="complementary",O60="Annual Pkg",O60="Deluxe Membership",O60="Premium Membership",O60="Hair Salon",O60="Customized Voucher",O60="Gift Voucher"),0,J60-L60) -> 0 | R60: =IFERROR(IF(VLOOKUP(G60, $Z$7:$AC$220, 4, FALSE) = 0, (F60 - E60) * 1440, VLOOKUP(G60, $Z$7:$AC$220, 4, FALSE)), (F60 - E60) * 1440) -> 0 | S60: =IFERROR(VLOOKUP(G60,$Z$7:$AC$220,3,FALSE),0) -> 0 | Y60: 54 | Z60: Standard Hair Waxing- Brazilian/Bikini Wax | AA60: 3000 | AB60: Beauty Salon
A61: =IF(B61<>"", MAX(A$6:A60)+1, "") | I61: =IFERROR(VLOOKUP(G61,$Z$7:$AA$220,2,FALSE),0) -> 0 | J61: =H61*I61 -> 0 | L61: =J61*K61 -> 0 | M61: =if(or(O61="complementary",O61="Annual Pkg",O61="Deluxe Membership",O61="Premium Membership",O61="Hair Salon",O61="Customized Voucher",O61="Gift Voucher"),0,J61-L61) -> 0 | R61: =IFERROR(IF(VLOOKUP(G61, $Z$7:$AC$220, 4, FALSE) = 0, (F61 - E61) * 1440, VLOOKUP(G61, $Z$7:$AC$220, 4, FALSE)), (F61 - E61) * 1440) -> 0 | S61: =IFERROR(VLOOKUP(G61,$Z$7:$AC$220,3,FALSE),0) -> 0 | Y61: 55 | Z61: Standard Hair Wax- Full Body(Without Brazilian Wax) | AA61: 6999 | AB61: Beauty Salon
A62: =IF(B62<>"", MAX(A$6:A61)+1, "") | I62: =IFERROR(VLOOKUP(G62,$Z$7:$AA$220,2,FALSE),0) -> 0 | J62: =H62*I62 -> 0 | L62: =J62*K62 -> 0 | M62: =if(or(O62="complementary",O62="Annual Pkg",O62="Deluxe Membership",O62="Premium Membership",O62="Hair Salon",O62="Customized Voucher",O62="Gift Voucher"),0,J62-L62) -> 0 | R62: =IFERROR(IF(VLOOKUP(G62, $Z$7:$AC$220, 4, FALSE) = 0, (F62 - E62) * 1440, VLOOKUP(G62, $Z$7:$AC$220, 4, FALSE)), (F62 - E62) * 1440) -> 0 | S62: =IFERROR(VLOOKUP(G62,$Z$7:$AC$220,3,FALSE),0) -> 0 | Y62: 56 | Z62: Premium Hair Waxing- Full Arms | AA62: 1800 | AB62: Beauty Salon
... A77: =IF(B77<>"", MAX(A$6:A76)+1, "") | I77: =IFERROR(VLOOKUP(G77,$Z$7:$AA$220,2,FALSE),0) -> 0 | J77: =H77*I77 -> 0 | L77: =J77*K77 -> 0 | M77: =if(or(O77="complementary",O77="Annual Pkg",O77="Deluxe Membership",O77="Premium Membership",O77="Hair Salon",O77="Customized Voucher",O77="Gift Voucher"),0,J77-L77) -> 0 | R77: =IFERROR(IF(VLOOKUP(G77, $Z$7:$AC$220, 4, FALSE) = 0, (F77 - E77) * 1440, VLOOKUP(G77, $Z$7:$AC$220, 4, FALSE)), (F77 - E77) * 1440) -> 0 | S77: =IFERROR(VLOOKUP(G77,$Z$7:$AC$220,3,FALSE),0) -> 0 | Y77: 71 | Z77: Threading-Chin | AA77: 150 | AB77: Beauty Salon
B78: Total | J78: =SUM(J7:J77) -> 0 | L78: =SUM(L7:L77) -> 0 | M78: =SUM(M7:M77) -> 0 | R78: =sum(R7:R77) -> 0 | Y78: 72 | Z78: Threading-Full Face | AA78: 700 | AB78: Beauty Salon
Y79: 73 | Z79: HIMALAYAN SALT SCRUB-60 Min+ Aromatherapy-60 Min | AA79: 7800 | AB79: Spa & Beauty Salon Combo | AC79: 120
Y80: 74 | Z80: HIMALAYAN SALT SCRUB-90 Min+ Aromatherapy-60 Min | AA80: 9500 | AB80: Spa & Beauty Salon Combo | AC80: 150
Y81: 75 | Z81: HIMALAYAN SALT SCRUB-120 Min+ Aromatherapy-60 Min | AA81: 11000 | AB81: Spa & Beauty Salon Combo | AC81: 180
Y82: 76 | Z82: COCONUT SCRUB WITH COFFEE-60 Min+ Aromatherapy-60 Min | AA82: 7800 | AB82: Spa & Beauty Salon Combo | AC82: 120
Y83: 77 | Z83: COCONUT SCRUB WITH COFFEE-90 Min+ Aromatherapy-60 Min | AA83: 9500 | AB83: Spa & Beauty Salon Combo | AC83: 150
Y84: 78 | Z84: COCONUT SCRUB WITH COFFEE-120 Min+ Aromatherapy-60 Min | AA84: 11000 | AB84: Spa & Beauty Salon Combo | AC84: 180
A85: SPA Signature Prepared By | G85: SPA Signature Verified By | N85: FO Signature | Y85: 79 | Z85: ROSE BODY SCRUB-60 Min+ Aromatherapy-60 Min | AA85: 8200 | AB85: Spa & Beauty Salon Combo | AC85: 120
A86: Name: | G86: Name: | N86: Name: | Y86: 80 | Z86: ROSE BODY SCRUB-90 Min+ Aromatherapy-60 Min | AA86: 9800 | AB86: Spa & Beauty Salon Combo | AC86: 150
Y87: 81 | Z87: ROSE BODY SCRUB-120 Min+ Aromatherapy-60 Min | AA87: 11300 | AB87: Spa & Beauty Salon Combo | AC87: 180
Y88: 82 | Z88: JASMINE BODY SCRUB-60 Min+ Aromatherapy-60 Min | AA88: 7800 | AB88: Spa & Beauty Salon Combo | AC88: 120
Y89: 83 | Z89: JASMINE BODY SCRUB-90 Min+ Aromatherapy-60 Min | AA89: 9500 | AB89: Spa & Beauty Salon Combo | AC89: 150
Y90: 84 | Z90: JASMINE BODY SCRUB-120 Min+ Aromatherapy-60 Min | AA90: 11000 | AB90: Spa & Beauty Salon Combo | AC90: 180
Y91: 85 | Z91: HONEY SANDALWOOD BODY SCRUB-60 Min+ Aromatherapy-60 Min | AA91: 8400 | AB91: Spa & Beauty Salon Combo | AC91: 120
Y92: 86 | Z92: HONEY SANDALWOOD BODY SCRUB-90 Min+ Aromatherapy-60 Min | AA92: 10000 | AB92: Spa & Beauty Salon Combo | AC92: 150
Y93: 87 | Z93: HONEY SANDALWOOD BODY SCRUB-120 Min+ Aromatherapy-60 Min | AA93: 11500 | AB93: Spa & Beauty Salon Combo | AC93: 180
Y94: 88 | Z94: BODY SCRUB-30 MIN | AA94: 2500 | AB94: Beauty Salon | AC94: 30
Y95: 89 | Z95: BODY SCRUB-45 MIN | AA95: 3500 | AB95: Beauty Salon | AC95: 45
Y96: 90 | Z96: BODY SCRUB-60 MIN | AA96: 4500 | AB96: Beauty Salon | AC96: 60
Y97: 91 | Z97: Women-Hair Cut | AA97: 800 | AB97: Hair Salon | AC97: 30
Y98: 92 | Z98: Women-Hair Trim | AA98: 500 | AB98: Hair Salon | AC98: 30
... Y111: 105 | Z111: COLOR TOUCH UP-Root Touchup (Ammonia Free) | AA111: 2200 | AB111: Hair Salon | AC111: 90
Y112: 106 | Z112: GLOBAL COLOR-Short Hair | AA112: 4000 | AB112: Hair Salon
Y113: 107 | Z113: GLOBAL COLOR-Medium Hair | AA113: 5000 | AB113: Hair Salon
Y114: 108 | Z114: GLOBAL COLOR-Long Hair | AA114: 6000 | AB114: Hair Salon
Y115: 109 | Z115: GLOBAL COLOR-Add Hair Bond Treatment | AA115: 1000 | AB115: Hair Salon
Y116: 110 | Z116: GLOBAL COLOR AMMONIA FREE-Short Hair | AA116: 5000 | AB116: Hair Salon
Y117: 111 | Z117: GLOBAL COLOR AMMONIA FREE-Medium Hair | AA117: 6000 | AB117: Hair Salon
Y118: 112 | Z118: GLOBAL COLOR AMMONIA FREE-Long Hair | AA118: 7000 | AB118: Hair Salon
Y119: 113 | Z119: GLOBAL HIGHLIGHT-Short Hair | AA119: 3500 | AB119: Hair Salon
Y120: 114 | Z120: GLOBAL HIGHLIGHT-Medium Hair | AA120: 4500 | AB120: Hair Salon
Y121: 115 | Z121: GLOBAL HIGHLIGHT-Long Hair | AA121: 6000 | AB121: Hair Salon
Y122: 116 | Z122: GLOBAL HIGHLIGHT-Hair Bond Treatment | AA122: 1000 | AB122: Hair Salon
Y123: 117 | Z123: GLOBAL HIGHLIGHT-Highlight per Stand | AA123: 250 | AB123: Hair Salon
... Y183: 177 | Z183: Men's Hair Cut Package | AA183: 6666 | AB183: Salon Package
Y184: 178 | Z184: HUA HIN-90 MIN | AA184: 6400 | AB184: Spa | AC184: 90
Y185: 179 | Z185: HUA HIN-120 MIN | AA185: 8000 | AB185: Spa | AC185: 120
Y186: 180 | Z186: Complete wellness gift - Single | AA186: 8999 | AB186: Current Package
Y187: 181 | Z187: Complete wellness gift - Couple | AA187: 16499 | AB187: Current Package
Y188: 182 | Z188: Couple Massage Wellness Date | AA188: 8499 | AB188: Current Package
Y189: 183 | Z189: Products | AA189: 1000 | AB189: Products
Y190: 184 | Z190: Standard Facial-Instafair-60min | AA190: 2500 | AB190: Beauty Salon | AC190: 60
Y191: 185 | Z191: Valentine Gift Hamper | AA191: 3000 | AB191: Gift Hamper
Y192: 186 | Z192: Valentine Gift Hamper package | AA192: 5999 | AB192: Gift Hamper Package
...

Sheet Booking
A1: Nuad Thai Nepal
A2: Date : | B2: ='Sales Report'!B4 -> 46012 | E2: Reception: …………………………
A4: TIME | C4: ROOM 1 | D4: ROOM 2 | E4: ROOM 3 | F4: ROOM 4 | G4: ROOM 5 | H4: ROOM 6 | I4: ROOM 7 | J4: ROOM 8 | K4: ROOM 9 | L4: SalonS | M4: PMM/FACIAL
A5: 9:00 AM | B5: 0
B6: 15
B7: 30
B8: 45
A9: 10:00 AM | B9: 0
B10: 15
B11: 30
B12: 45
A13: 11:00 AM | B13: 0
B14: 15
B15: 30
B16: 45
A17: 12:00 PM | B17: 0
B18: 15
B19: 30
B20: 45
A21: 1:00 PM | B21: 0
B22: 15
B23: 30
B24: 45
A25: 2:00 PM | B25: 0
B26: 15
B27: 30
B28: 45
A29: 3:00PM | B29: 0
B30: 15
B31: 30
B32: 45
A33: 4:00PM | B33: 0
B34: 15
B35: 30
B36: 45
A37: 5:00PM | B37: 0
B38: 15
B39: 30
B40: 45
A41: 6:00PM | B41: 0
B42: 15
B43: 30
B44: 45
A45: 7:00PM | B45: 0
B46: 15
B47: 30
B48: 45
A49: 8:00PM | B49: 0
B50: 15
B51: 30
B52: 45

Sheet SUMMARY
A1: ='Sales Report'!A1 -> NUAD THAI NEPAL Lazimpat
A2: Summary Sales Report
A3: ='Sales Report'!B4 -> 46012
A4: Mode of Payment | B4: Sales Amount | D4: Staff Name | E4: Working Hours(Min) | F4: Working Hours | G4: Remarks
A5: Cash | B5: =sumif('Sales Report'!$O$7:$O$77,A5,'Sales Report'!$M$7:$M$77) -> 0 | D5: =Attendance!B8 | E5: =SUMIF('Sales Report'!$P$7:$P$77,D5,'Sales Report'!$R$7:$R$77) -> 0 | F5: =IF(E5>0, INT(E5/60) & " hr and " & MOD(E5, 60) & " min", "-") -> -
A6: Card | B6: =sum(B7:B9) -> 0 | D6: =Attendance!B9 | E6: =SUMIF('Sales Report'!$P$7:$P$77,D6,'Sales Report'!$R$7:$R$77) -> 0 | F6: =IF(E6>0, INT(E6/60) & " hr and " & MOD(E6, 60) & " min", "-") -> -
A7: Nabil Card | B7: =sumif('Sales Report'!$O$7:$O$77,A7,'Sales Report'!$M$7:$M$77) -> 0 | D7: =Attendance!B10 | E7: =SUMIF('Sales Report'!$P$7:$P$77,D7,'Sales Report'!$R$7:$R$77) -> 0 | F7: =IF(E7>0, INT(E7/60) & " hr and " & MOD(E7, 60) & " min", "-") -> -
A8: Global IME Card | B8: =sumif('Sales Report'!$O$7:$O$77,A8,'Sales Report'!$M$7:$M$77) -> 0 | D8: =Attendance!B11 | E8: =SUMIF('Sales Report'!$P$7:$P$77,D8,'Sales Report'!$R$7:$R$77) -> 0 | F8: =IF(E8>0, INT(E8/60) & " hr and " & MOD(E8, 60) & " min", "-") -> -
A9: Nic Asia Card | B9: =sumif('Sales Report'!$O$7:$O$77,A9,'Sales Report'!$M$7:$M$77) -> 0 | D9: =Attendance!B12 | E9: =SUMIF('Sales Report'!$P$7:$P$77,D9,'Sales Report'!$R$7:$R$77) -> 0 | F9: =IF(E9>0, INT(E9/60) & " hr and " & MOD(E9, 60) & " min", "-") -> -
A10: Fonepay | B10: =sumif('Sales Report'!$O$7:$O$77,A10,'Sales Report'!$M$7:$M$77) -> 0 | D10: =Attendance!B13 | E10: =SUMIF('Sales Report'!$P$7:$P$77,D10,'Sales Report'!$R$7:$R$77) -> 0 | F10: =IF(E10>0, INT(E10/60) & " hr and " & MOD(E10, 60) & " min", "-") -> -
A11: Credit | B11: =sumif('Sales Report'!$O$7:$O$77,A11,'Sales Report'!$M$7:$M$77) -> 0 | D11: =Attendance!B14 | E11: =SUMIF('Sales Report'!$P$7:$P$77,D11,'Sales Report'!$R$7:$R$77) -> 0 | F11: =IF(E11>0, INT(E11/60) & " hr and " & MOD(E11, 60) & " min", "-") -> -
A12: Cheque | B12: =sumif('Sales Report'!$O$7:$O$77,A12,'Sales Report'!$M$7:$M$77) -> 0 | D12: =Attendance!B15 | E12: =SUMIF('Sales Report'!$P$7:$P$77,D12,'Sales Report'!$R$7:$R$77) -> 0 | F12: =IF(E12>0, INT(E12/60) & " hr and " & MOD(E12, 60) & " min", "-") -> -
A13: Total | B13: =B5+B6+B10+B11+B12 -> 0 | D13: =Attendance!B16 | E13: =SUMIF('Sales Report'!$P$7:$P$77,D13,'Sales Report'!$R$7:$R$77) -> 0 | F13: =IF(E13>0, INT(E13/60) & " hr and " & MOD(E13, 60) & " min", "-") -> -
A14: Complementary | B14: =sumif('Sales Report'!O7:O77,A14,'Sales Report'!J7:J77) -> 0 | D14: =Attendance!B17 | E14: =SUMIF('Sales Report'!$P$7:$P$77,D14,'Sales Report'!$R$7:$R$77) -> 0 | F14: =IF(E14>0, INT(E14/60) & " hr and " & MOD(E14, 60) & " min", "-") -> -
D15: =Attendance!B18 | E15: =SUMIF('Sales Report'!$P$7:$P$77,D15,'Sales Report'!$R$7:$R$77) -> 0 | F15: =IF(E15>0, INT(E15/60) & " hr and " & MOD(E15, 60) & " min", "-") -> -
D16: =Attendance!B19 | E16: =SUMIF('Sales Report'!$P$7:$P$77,D16,'Sales Report'!$R$7:$R$77) -> 0 | F16: =IF(E16>0, INT(E16/60) & " hr and " & MOD(E16, 60) & " min", "-") -> -
D17: =Attendance!B20 | E17: =SUMIF('Sales Report'!$P$7:$P$77,D17,'Sales Report'!$R$7:$R$77) -> 0 | F17: =IF(E17>0, INT(E17/60) & " hr and " & MOD(E17, 60) & " min", "-") -> -
D18: =Attendance!B21 | E18: =SUMIF('Sales Report'!$P$7:$P$77,D18,'Sales Report'!$R$7:$R$77) -> 0 | F18: =IF(E18>0, INT(E18/60) & " hr and " & MOD(E18, 60) & " min", "-") -> -
D19: =Attendance!B22 | E19: =SUMIF('Sales Report'!$P$7:$P$77,D19,'Sales Report'!$R$7:$R$77) -> 0 | F19: =IF(E19>0, INT(E19/60) & " hr and " & MOD(E19, 60) & " min", "-") -> -
D20: =Attendance!B22 | E20: =SUMIF('Sales Report'!$P$7:$P$77,D20,'Sales Report'!$R$7:$R$77) -> 0 | F20: =IF(E20>0, INT(E20/60) & " hr and " & MOD(E20, 60) & " min", "-") -> -
D21: =Attendance!B23 | E21: =SUMIF('Sales Report'!$P$7:$P$77,D21,'Sales Report'!$R$7:$R$77) -> 0 | F21: =IF(E21>0, INT(E21/60) & " hr and " & MOD(E21, 60) & " min", "-") -> -
D22: =Attendance!B24 | E22: =SUMIF('Sales Report'!$P$7:$P$77,D22,'Sales Report'!$R$7:$R$77) -> 0 | F22: =IF(E22>0, INT(E22/60) & " hr and " & MOD(E22, 60) & " min", "-") -> -
D23: =Attendance!B25 | E23: =SUMIF('Sales Report'!$P$7:$P$77,D23,'Sales Report'!$R$7:$R$77) -> 0 | F23: =IF(E23>0, INT(E23/60) & " hr and " & MOD(E23, 60) & " min", "-") -> -
D24: =Attendance!B26 | E24: =SUMIF('Sales Report'!$P$7:$P$77,D24,'Sales Report'!$R$7:$R$77) -> 0 | F24: =IF(E24>0, INT(E24/60) & " hr and " & MOD(E24, 60) & " min", "-") -> -
D25: =Attendance!B27 | E25: =SUMIF('Sales Report'!$P$7:$P$77,D25,'Sales Report'!$R$7:$R$77) -> 0 | F25: =IF(E25>0, INT(E25/60) & " hr and " & MOD(E25, 60) & " min", "-") -> -
D26: =Attendance!B28 | E26: =SUMIF('Sales Report'!$P$7:$P$77,D26,'Sales Report'!$R$7:$R$77) -> 0 | F26: =IF(E26>0, INT(E26/60) & " hr and " & MOD(E26, 60) & " min", "-") -> -
D27: =Attendance!B29 | F27: =IF(E27>0, INT(E27/60) & " hr and " & MOD(E27, 60) & " min", "-") -> -
D28: Total | E28: =SUM(E5:E26) -> 0 | F28: =IF(E28>0, INT(E28/60) & " hr and " & MOD(E28, 60) & " min", "0") -> 0
